setup.cfg
setup.py
bin/labellio_classify
labellio/__init__.py
labellio/classifier.py
labellio/config.py
labellio/image.py
labellio/label.py
labellio/mean.py
labellio/net.py
labellio_cli2.egg-info/PKG-INFO
labellio_cli2.egg-info/SOURCES.txt
labellio_cli2.egg-info/dependency_links.txt
labellio_cli2.egg-info/requires.txt
labellio_cli2.egg-info/top_level.txt