Metadata-Version: 1.1
Name: labellio-cli2
Version: 0.0.5
Summary: Labellio command line interface
Home-page: https://github.com/kccsairc/labellio_cli
Author: AlpacaDB, Inc.
Author-email: UNKNOWN
License: MIT
Keywords: deep learning caffe labellio kccs kyocera
Platform: UNKNOWN
Classifier: Development Status :: 3 - Alpha
Classifier: Intended Audience :: Information Technology
Classifier: License :: OSI Approved :: MIT License
Classifier: Programming Language :: Python :: 2.7
